multirunnable/__init__.py
multirunnable/__pkg_info__.py
multirunnable/_config.py
multirunnable/_import_utils.py
multirunnable/_singletons.py
multirunnable/_utils.py
multirunnable/exceptions.py
multirunnable/executor.py
multirunnable/mode.py
multirunnable/pool.py
multirunnable/tasks.py
multirunnable/types.py
multirunnable/adapter/__init__.py
multirunnable/adapter/communication.py
multirunnable/adapter/context.py
multirunnable/adapter/lock.py
multirunnable/api/__init__.py
multirunnable/api/_retry.py
multirunnable/api/decorator.py
multirunnable/api/exceptions.py
multirunnable/api/manage.py
multirunnable/api/operator.py
multirunnable/concurrent/__init__.py
multirunnable/concurrent/context.py
multirunnable/concurrent/queue.py
multirunnable/concurrent/result.py
multirunnable/concurrent/strategy.py
multirunnable/concurrent/synchronization.py
multirunnable/coroutine/__init__.py
multirunnable/coroutine/context.py
multirunnable/coroutine/queue.py
multirunnable/coroutine/result.py
multirunnable/coroutine/strategy.py
multirunnable/coroutine/synchronization.py
multirunnable/coroutine/utils.py
multirunnable/factory/__init__.py
multirunnable/factory/_utils.py
multirunnable/factory/base.py
multirunnable/factory/collection.py
multirunnable/factory/communication.py
multirunnable/factory/lock.py
multirunnable/factory/queue.py
multirunnable/factory/strategy.py
multirunnable/framework/__init__.py
multirunnable/framework/executor.py
multirunnable/framework/pool.py
multirunnable/framework/task.py
multirunnable/framework/adapter/__init__.py
multirunnable/framework/adapter/lock.py
multirunnable/framework/api/__init__.py
multirunnable/framework/api/operator.py
multirunnable/framework/factory/__init__.py
multirunnable/framework/factory/base.py
multirunnable/framework/factory/collection.py
multirunnable/framework/runnable/__init__.py
multirunnable/framework/runnable/context.py
multirunnable/framework/runnable/queue.py
multirunnable/framework/runnable/result.py
MultiRunnable-0.17.0.dist-info/LICENSE
MultiRunnable-0.17.0.dist-info/METADATA
MultiRunnable-0.17.0.dist-info/WHEEL
MultiRunnable-0.17.0.dist-info/top_level.txt
MultiRunnable-0.17.0.dist-info/RECORD
